hubspot_oauth2client/__init__.py
hubspot_oauth2client/client.py
hubspot_oauth2client-0.1.dist-info/DESCRIPTION.rst
hubspot_oauth2client-0.1.dist-info/METADATA
hubspot_oauth2client-0.1.dist-info/RECORD
hubspot_oauth2client-0.1.dist-info/WHEEL
hubspot_oauth2client-0.1.dist-info/metadata.json
hubspot_oauth2client-0.1.dist-info/top_level.txt
